CHANGELOG.txt
LICENSE.txt
MANIFEST.in
README.rst
pyproject.toml
setup.py
src/pyctools/setup.py
src/pyctools.core.egg-info/PKG-INFO
src/pyctools.core.egg-info/SOURCES.txt
src/pyctools.core.egg-info/dependency_links.txt
src/pyctools.core.egg-info/entry_points.txt
src/pyctools.core.egg-info/not-zip-safe
src/pyctools.core.egg-info/requires.txt
src/pyctools.core.egg-info/top_level.txt
src/pyctools/components/arithmetic.py
src/pyctools/components/framerepeat.py
src/pyctools/components/modulate.py
src/pyctools/components/colourspace/__init__.py
src/pyctools/components/colourspace/adjustsaturation.py
src/pyctools/components/colourspace/extractcomps.py
src/pyctools/components/colourspace/gammacorrection.py
src/pyctools/components/colourspace/gammacorrectioncore.c
src/pyctools/components/colourspace/histogramequalisation.py
src/pyctools/components/colourspace/levels.py
src/pyctools/components/colourspace/matrices.py
src/pyctools/components/colourspace/matrix.py
src/pyctools/components/colourspace/quantise.py
src/pyctools/components/colourspace/rgbtoy.py
src/pyctools/components/colourspace/rgbtoyuv.py
src/pyctools/components/colourspace/yuvtorgb.py
src/pyctools/components/deinterlace/__init__.py
src/pyctools/components/deinterlace/halfsize.py
src/pyctools/components/deinterlace/hhiprefilter.py
src/pyctools/components/deinterlace/intrafield.py
src/pyctools/components/deinterlace/simple.py
src/pyctools/components/deinterlace/weston3field.py
src/pyctools/components/fft/__init__.py
src/pyctools/components/fft/fft.py
src/pyctools/components/fft/tile.py
src/pyctools/components/fft/window.py
src/pyctools/components/interp/__init__.py
src/pyctools/components/interp/filterdesign.py
src/pyctools/components/interp/filtergenerator.py
src/pyctools/components/interp/gaussianfilter.py
src/pyctools/components/interp/imageresizer.py
src/pyctools/components/interp/resize.py
src/pyctools/components/interp/resizecore.c
src/pyctools/components/io/__init__.py
src/pyctools/components/io/dumpmetadata.py
src/pyctools/components/io/imagedisplay.py
src/pyctools/components/io/imagefilecv.py
src/pyctools/components/io/imagefilepil.py
src/pyctools/components/io/imagefilereader.py
src/pyctools/components/io/imagefilewriter.py
src/pyctools/components/io/imagesequencereader.py
