Metadata-Version: 2.1
Name: pyctools.core
Version: 0.7.0
Summary: Picture processing algorithm development kit
Author-email: Jim Easterbrook <jim@jim-easterbrook.me.uk>
License: GNU GPL
Project-URL: homepage, https://github.com/jim-easterbrook/pyctools
Project-URL: documentation, https://pyctools.readthedocs.io/
Project-URL: repository, https://github.com/jim-easterbrook/pyctools
Project-URL: changelog, https://github.com/jim-easterbrook/pyctools/blob/main/CHANGELOG.txt
Platform: POSIX
Platform: MacOS
Classifier: Development Status :: 3 - Alpha
Classifier: Intended Audience :: Developers
Classifier: Intended Audience :: Science/Research
Classifier: License :: OSI Approved :: GNU General Public License v3 or later (GPLv3+)
Classifier: Operating System :: MacOS
Classifier: Operating System :: MacOS :: MacOS X
Classifier: Operating System :: POSIX
Classifier: Operating System :: POSIX :: BSD :: FreeBSD
Classifier: Operating System :: POSIX :: BSD :: NetBSD
Classifier: Operating System :: POSIX :: Linux
Classifier: Programming Language :: Python :: 3
Classifier: Topic :: Multimedia :: Graphics
Classifier: Topic :: Multimedia :: Video
Classifier: Topic :: Scientific/Engineering :: Image Recognition
Classifier: Topic :: Scientific/Engineering :: Visualization
Requires-Python: >=3.6
License-File: LICENSE.txt
Requires-Dist: docutils
Requires-Dist: exiv2>=0.11
Requires-Dist: numpy<2
Requires-Dist: pillow
Provides-Extra: pyqt5
Requires-Dist: PyQt5>=5.9; extra == "pyqt5"
Provides-Extra: pyqt6
Requires-Dist: pyctools-core[PyQt6-linux]; platform_system == "Linux" and extra == "pyqt6"
Requires-Dist: pyctools-core[PyQt6-darwin]; platform_system == "Darwin" and extra == "pyqt6"
Provides-Extra: pyside2
Requires-Dist: PySide2>=5.11.1; python_version < "3.8" and extra == "pyside2"
Requires-Dist: PySide2>=5.14; python_version >= "3.8" and extra == "pyside2"
Provides-Extra: pyside6
Requires-Dist: pyctools-core[PySide6-linux]; platform_system == "Linux" and extra == "pyside6"
Requires-Dist: pyctools-core[PySide6-darwin]; platform_system == "Darwin" and extra == "pyside6"
Provides-Extra: pyqt6-linux
Requires-Dist: PyQt6>=6.2; python_version != "3.6.*" and extra == "pyqt6-linux"
Requires-Dist: PyQt6<6.3,>=6.2; python_version == "3.6.*" and extra == "pyqt6-linux"
Requires-Dist: PyQt6-Qt6<6.3; python_version == "3.6.*" and extra == "pyqt6-linux"
Provides-Extra: pyqt6-darwin
Requires-Dist: PyQt6>=6.2; extra == "pyqt6-darwin"
Requires-Dist: PyQt6-Qt6!=6.6.1,>=6.2; extra == "pyqt6-darwin"
Provides-Extra: pyside6-linux
Requires-Dist: PySide6>=6.2; extra == "pyside6-linux"
Provides-Extra: pyside6-darwin
Requires-Dist: PySide6!=6.6.1,>=6.2; extra == "pyside6-darwin"
Provides-Extra: cv2
Requires-Dist: pyctools-core[OpenCV]; extra == "cv2"
Provides-Extra: matplotlib
Requires-Dist: matplotlib; extra == "matplotlib"
Provides-Extra: opencv
Requires-Dist: opencv-python-headless; python_version != "3.6.*" and extra == "opencv"
Requires-Dist: opencv-python-headless<4.7; python_version == "3.6.*" and extra == "opencv"
Provides-Extra: opengl
Requires-Dist: pyctools-core[PyOpenGL]; extra == "opengl"
Provides-Extra: pyopengl
Requires-Dist: PyOpenGL; extra == "pyopengl"
Requires-Dist: PyOpenGL-accelerate; extra == "pyopengl"
Provides-Extra: rawkit
Requires-Dist: rawkit; extra == "rawkit"
Provides-Extra: rawpy
Requires-Dist: rawpy; extra == "rawpy"
Provides-Extra: scipy
Requires-Dist: scipy; extra == "scipy"
Provides-Extra: all
Requires-Dist: pyctools-core[OpenCV,PyOpenGL,SciPy,matplotlib,rawkit,rawpy]; extra == "all"
